talib/__init__.py
talib/_ta_lib.cpython-36m-x86_64-linux-gnu.so
talib/abstract.py
talib/deprecated.py
talib/stream.py
talib/test_abstract.py
talib/test_data.py
talib/test_func.py
talib/test_pandas.py
talib/test_stream.py
talib/.libs/libta_lib-9f3023b9.so.0.0.0
talib_binary-0.4.18.dist-info/top_level.txt
talib_binary-0.4.18.dist-info/WHEEL
talib_binary-0.4.18.dist-info/METADATA
talib_binary-0.4.18.dist-info/RECORD
